<?xml version="1.0" encoding="utf-8"?>
  <?xml-stylesheet type="text/xsl" href="rfc2629.xslt" ?>
  <!-- generated by https://github.com/cabo/kramdown-rfc2629 version 1.4.19 -->

<!DOCTYPE rfc SYSTEM "rfc2629.dtd" [
]>

<?rfc toc="yes"?>
<?rfc sortrefs="yes"?>
<?rfc symrefs="yes"?>
<?rfc comments="yes"?>

<rfc ipr="trust200902" docName="draft-yg3bp-ccamp-optical-inventory-yang-01" category="std">

  <front>
    <title abbrev="Optical Inventory YANG">A YANG Data Model for Optical Network Inventory</title>

    <author initials="C." surname="Yu" fullname="Chaode Yu">
      <organization>Huawei Technologies</organization>
      <address>
        <email>yuchaode@huawei.com</email>
      </address>
    </author>
    <author initials="I." surname="Busi" fullname="Italo Busi">
      <organization>Huawei Technologies</organization>
      <address>
        <email>italo.busi@huawei.com</email>
      </address>
    </author>
    <author initials="A." surname="Guo" fullname="Aihua Guo">
      <organization>Futurewei Technologies</organization>
      <address>
        <email>aihuaguo.ietf@gmail.com</email>
      </address>
    </author>
    <author initials="S." surname="Belotti" fullname="Sergio Belotti">
      <organization>Nokia</organization>
      <address>
        <email>sergio.belotti@nokia.com</email>
      </address>
    </author>
    <author initials="J-F." surname="Bouquier" fullname="Jean-Francois Bouquier">
      <organization>Vodafone</organization>
      <address>
        <email>jeff.bouquier@vodafone.com</email>
      </address>
    </author>
    <author initials="F." surname="Peruzzini" fullname="Fabio Peruzzini">
      <organization>TIM</organization>
      <address>
        <email>fabio.peruzzini@telecomitalia.it</email>
      </address>
    </author>
    <author initials="O.G.d." surname="Dios" fullname="Oscar Gonzalez de Dios">
      <organization>Telefonica</organization>
      <address>
        <email>oscar.gonzalezdedios@telefonica.com</email>
      </address>
    </author>
    <author initials="V." surname="Lopez" fullname="Victor Lopez">
      <organization>Nokia</organization>
      <address>
        <email>victor.lopez@nokia.com</email>
      </address>
    </author>
    <author initials="H." surname="Zheng" fullname="Haomian Zheng">
      <organization>Huawei Technologies</organization>
      <address>
        <email>zhenghaomian@huawei.com</email>
      </address>
    </author>

    <date year="2021" month="October" day="25"/>

    
    <workgroup>CCAMP Working Group</workgroup>
    

    <abstract>


<t>This document defines a YANG data model for optical network inventory data information.</t>

<t>The YANG data model presented in this document is intended to be used as the basis toward a generic YANG data model for network inventory data information which can be augmented, when required, with technology-specific (e.g., optical) inventory data, to be defined either in a future version of this document or in another document.</t>

<t>The YANG data model defined in this document conforms to the Network Management Datastore Architecture (NMDA).</t>



    </abstract>


  </front>

  <middle>


<section anchor="introduction"><name>Introduction</name>

<t>Network inventory management is a key component in operators' OSS architectures.</t>

<t>Network inventory is a fundamental functionality in network management
  and was specified many years ago. Given the emerging of data models and 
  their deployment in operator's management and control systems, the traditional function of inventory management
  is also requested to be defined as a data model.</t>

<t>Network inventory management and monitoring is a critical part of 
  ensuring the network stays healthy, well-planned, and functioning 
  in the operator's network. Network inventory management allows the
  operator to keep track of what physical network devices are staying
  in the network including relevant software and hardware.</t>

<t>The network inventory management also helps the operator to know when 
  to acquire new assets and what is needed, or to decommission old or faulty ones, 
  which can help to improve network performance and capacity planning.</t>

<t>In <xref target="I-D.ietf-teas-actn-poi-applicability"/> a gap was identified regarding the lack of a YANG data model that could be used at ACTN MPI interface level to report whole/partial hardware inventory information available at PNC level towards north-bound systems (e.g., MDSC or OSS layer).</t>

<t><xref target="RFC8345"/> initial goal was to make possible the augmentation of the YANG data model with network inventory data model but this was never developed and the scope was kept limited to network topology data only.</t>

<t>It is key for operators to drive the industry towards the use of a standard YANG data model for network inventory data instead of using vendors proprietary APIs (e.g., REST API).</t>

<t>In the ACTN architecture, this would bring also clear benefits at MDSC level for packet over optical integration scenarios since this would enable the correlation of the inventory information with the links information reported in the network topology model.</t>

<t>The intention is to define a generic YANG data model that would be as much as possible technology agnostic (valid for IP, optical and microwave networks) and that could be augmented, when required, to include some technology-specific inventory details.</t>

<t><xref target="RFC8348"/> defines a YANG data model for the management of the hardware on a single server and therefore it is more applicable to the PNC South Bound Interface (SBI) towards the network elements rather than at the PNC MPI. However, the YANG data model defined in <xref target="RFC8348"/> has been used as a reference for defining the YANG network inventory data model.</t>

<t>For optical network inventory, the network inventory YANG data model should support the use cases (4a and 4b) and requirements defined in <xref target="ONF_TR-547"/>, in order to guarantee a seamless integration at MDSC/OSS/orchestration layers.</t>

<t>The proposed YANG data model has been analysed to cover the requirements and use cases for Optical Network Inventory.</t>

<t>Being based on <xref target="RFC8348"/>, this data model should be a good starting point toward a generic data model and applicable to any technology. However, further analysis of requirements and use cases is needed to extend the applicability of this YANG data model to other types of networks (IP and microwave) and to identify which aspects are generic and which aspects are technology-specific for optical networks.</t>

<t>This document defines one YANG module: ietf-network-inventory.yang (<xref target="ni-yang"/>).</t>

<t>Note: review in future versions of this document the related modules, depending on the augmentation relationship.</t>

<t>The YANG data model defined in this document conforms to the Network Management Datastore Architecture <xref target="RFC8342"/>.</t>

<section anchor="terminology-and-notations"><name>Terminology and Notations</name>

<t>Refer to <xref target="RFC7446"/> and <xref target="RFC7581"/> for the key terms used in this
  document.  The following terms are defined in <xref target="RFC7950"/> and are not
  redefined here:</t>

<t><list style="symbols">
  <t>client</t>
  <t>server</t>
  <t>augment</t>
  <t>data model</t>
  <t>data node</t>
</list></t>

<t>The following terms are defined in <xref target="RFC6241"/> and are not redefined
  here:</t>

<t><list style="symbols">
  <t>configuration data</t>
  <t>state data</t>
</list></t>

<t>The terminology for describing YANG data models is found in
  <xref target="RFC7950"/>.</t>

<t>TBD: Recap the concept of chassis/slot/component/board/... in <xref target="TMF-MTOSI"/>.</t>

<t>Following terms are used for the representation of the hierarchies in the 
  optical network inventory.</t>

<t>Network Element: a device installed on one or several shelves and can afford some specific transmission function independently.</t>

<t>Cabinet: a holder of the device and provides power supply for the device in it.</t>

<t>Chassis:  a holder of the device installation.</t>

<t>Slot: a holder of the board.</t>

<t>Component: holders and equipments of the network element, including rack, shelf, slot, sub-slot, board and port.</t>

<t>Board/Card: a pluggable equipment on the network element and can afford a specific transmission function independently.</t>

<t>Port: an interface on board</t>

</section>
<section anchor="tree-diagram"><name>Tree Diagram</name>

<t>A simplified graphical representation of the data model is used in <xref target="ni-tree"/> of this document.
The meaning of the symbols in these diagrams is defined in <xref target="RFC8340"/>.</t>

</section>
<section anchor="prefix-in-data-node-names"><name>Prefix in Data Node Names</name>

<t>In this document, names of data nodes and other data model objects
  are prefixed using the standard prefix associated with the
  corresponding YANG imported modules, as shown in the following table.</t>

<texttable title="Prefixes and corresponding YANG modules" anchor="tab-prefixes">
      <ttcol align='left'>Prefix</ttcol>
      <ttcol align='left'>Yang Module</ttcol>
      <ttcol align='left'>Reference</ttcol>
      <c>ianahw</c>
      <c>iana-hardware</c>
      <c><xref target="RFC8348"/></c>
      <c>ni</c>
      <c>ietf-network-inventory</c>
      <c>RFCXXX</c>
      <c>yang</c>
      <c>ietf-yang-types</c>
      <c><xref target="RFC6991"/></c>
</texttable>

<t>RFC Editor Note:
Please replace XXXX with the RFC number assigned to this document.
Please remove this note.</t>

</section>
</section>
<section anchor="yang-data-model-for-optical-network-inventory"><name>YANG Data Model for Optical Network Inventory</name>

<section anchor="yang-model-overview"><name>YANG Model Overview</name>

<t>Based on TMF classification in <xref target="TMF-MTOSI"/>, inventory objects can be divided into two groups, holder group and equipment group. The holder group contains rack, shelf, slot, sub-slot while the equipment group contains network-element, board and port. With the requirement of GIS and on-demand domain controller selection raised, the equipment room becomes a new inventory object to be managed besides TMF classification.</t>

<t>Logically,  the relationship between these inventory objects can be described by <xref target="fig-inventory-object-relationship"/> below:</t>

<figure title="Relationship between inventory objects" anchor="fig-inventory-object-relationship"><artwork><![CDATA[
                    +-------------+
                    |  inventory  |
                    +-------------+
                         ||
                         || 1:N
                         \/
                 +----------------+
                 | equipment room |
                 +----------------+
                         ||
                         || 
      _______1:N_________||_______1:M___________
      ||—————————————————  ———————————————————||
      ||                                      || 
      \/                                      \/
+------------+                        +-----------------+ 
|    rack    | /__________M:N________\| network element |
+------------+ \---------------------/+-----------------+
      ||                                 ||   ||
      || 1:N                             ||   ||
      \/                                 ||   ||
+------------+ /__________1:M____________||   ||
|   shelf    | \--------------------------|   ||   
+------------+                                ||
      ||__________________  __________________||
      |-------------------||-------------------|
      _________1:N________||________1:M_________
      ||------------------  ------------------||
      \/                                      \/
+---------------+                        +-----------+
| slot/su-bslot |                        |   board   |
+---------------+                        +-----------+
                                              ||
                                              || 1:N
                                              \/
                                         +-----------+
                                         |    port   |
                                         +-----------+
]]></artwork></figure>

<t>In <xref target="RFC8348"/>, rack, shelf, slot, sub-slot, board and port are defined as components of network elements with generic attributes.</t>

<t>While <xref target="RFC8348"/> is used to manage the hardware of a single server (e.g., a Network Element), the Network Inventory YANG data model is used to retrieve the network inventory information that a controller discovers from multiple Network Elements under its control.</t>

<t>However, the YANG data model defined in <xref target="RFC8348"/> has been used as a reference for defining the YANG network inventory data model. This approach can simplify the implementation of this network inventory model when the controller uses the YANG data model defined in <xref target="RFC8348"/> to retrieve the hardware configuration from the network elements under its control.</t>

<t>Note: review in future versions of this document which attributes from <xref target="RFC8348"/> are required also for network inventory and whether there are attributes not defined in <xref target="RFC8348"/>which are required for network inventory</t>

<t>Note: review in future versions of this document whether to re-use definitions from <xref target="RFC8348"/> or use schema-mount.</t>

<figure><artwork><![CDATA[
  +--ro network-inventory
     +--ro equipment-rooms
     |  +--ro equipment-room* [uuid]
     |     +--ro uuid        yang:uuid
     |     ...................................
     |     +--ro rack* [uuid]
     |        +--ro uuid           yang:uuid
     |        ...................................
     |        +--ro shelves* [uuid]
     |           +--ro uuid            yang:uuid
     |           ...................................
     |           +--ro chassis-ref
     |              +--ro ne-ref?          leafref
     |              +--ro component-ref?   leafref
     +--ro network-elements
        +--ro network-element* [uuid]
           +--ro uuid          yang:uuid
           ...................................
           +--ro components
              +--ro component* [uuid]
                 +--ro uuid              yang:uuid
                 ...................................
]]></artwork></figure>

<t>The YANG data model for network inventory follows the same approach of <xref target="RFC8348"/> and reports the network inventory as a list of components of different types (e.g., chassis, module, port).</t>

<figure><artwork><![CDATA[
  +--ro components
     +--ro component* [uuid]
        +--ro uuid              yang:uuid
        +--ro name?             string
        +--ro description?      string
        +--ro class?            identityref
        +--ro parent-rel-pos?   int32
        +--ro children* [child-ref]
        |  +--ro child-ref    -> ../../../../uuid
        +--ro parent
           +--ro parent-ref?   -> ../../../../uuid
]]></artwork></figure>

<t>Note: review in future versions of this document whether the component list should be under the network-inventory instead of under the network-element container</t>

<t>However, considering there are some special scenarios, the relationship between the rack and network elements is not 1 to 1 nor 1 to n. The network element cannot be the direct parent node of the rack. So there should be n to m relationship between racks and network elements.
And the shelves in the rack should have some reference information to the component.</t>

<t>Note that in <xref target="RFC8345"/>, topology and inventory are two subsets of network information. However, considering the complexity of the existing topology models and to have a better extension capability, we define a separate root for the inventory model. We will consider some other ways to do some associations between the topology model and inventory model in the future.</t>

<t>Note: review in future versions of this document whether network inventory should be defined as an augmentation of the network model defined in <xref target="RFC8345"/> instead of under a new network-inventory root.</t>

<t>The proposed YANG data model has been analysed to cover the requirements and use cases for Optical Network Inventory.</t>

<t>Further analysis of requirements and use cases is needed to extend the applicability of this YANG data model to other types of networks (IP and microwave) and to identify which aspects are generic and which aspects are technology-specific for optical networks.</t>

</section>
</section>
<section anchor="ni-tree"><name>Optical Network Inventory Tree Diagram</name>

<t><xref target="fig-ni-tree"/> below shows the tree diagram of the YANG data model defined in module ietf-network-inventory.yang (<xref target="ni-yang"/>).</t>

<figure title="Network inventory tree diagram" anchor="fig-ni-tree"><artwork><![CDATA[
module: ietf-network-inventory
  +--ro network-inventory
     +--ro equipment-rooms
     |  +--ro equipment-room* [uuid]
     |     +--ro uuid        yang:uuid
     |     +--ro name?       string
     |     +--ro location?   string
     |     +--ro rack* [uuid]
     |        +--ro uuid           yang:uuid
     |        +--ro name?          string
     |        +--ro row-number?    uint32
     |        +--ro rack-number?   uint32
     |        +--ro shelves* [uuid]
     |           +--ro uuid            yang:uuid
     |           +--ro name?           string
     |           +--ro shelf-number?   uint8
     |           +--ro chassis-ref
     |              +--ro ne-ref?          leafref
     |              +--ro component-ref?   leafref
     +--ro network-elements
        +--ro network-element* [uuid]
           +--ro uuid          yang:uuid
           +--ro name?         string
           +--ro components
              +--ro component* [uuid]
                 +--ro uuid              yang:uuid
                 +--ro name?             string
                 +--ro description?      string
                 +--ro class?            identityref
                 +--ro parent-rel-pos?   int32
                 +--ro children* [child-ref]
                 |  +--ro child-ref    -> ../../../../uuid
                 +--ro parent
                    +--ro parent-ref?   -> ../../../../uuid
]]></artwork></figure>

</section>
<section anchor="ni-yang"><name>YANG Model for Optical Network Inventory</name>

<figure title="Network inventory YANG module" anchor="fig-ni-yang"><artwork><![CDATA[
<CODE BEGINS> file "ietf-network-inventory@2021-10-25.yang"
module ietf-network-inventory {
  yang-version 1.1;
  namespace "urn:ietf:params:xml:ns:yang:ietf-network-inventory";
  prefix ni;

  import ietf-yang-types {
    prefix yang;
    reference
      "RFC6991: Common YANG Data Types.";
  }
  
  import iana-hardware {
    prefix ianahw;
    reference
      "RFC 8348: A YANG Data Model for Hardware Management.";
  }
  
  organization
    "IETF CCAMP Working Group";
  contact
    "WG Web:   <https://datatracker.ietf.org/wg/ccamp/>
     WG List:  <mailto:ccamp@ietf.org>

     Editor:   Chaode Yu
               <yuchaode@huawei.com>

     Editor:   Italo Busi
               <italo.busi@huawei.com>

     Editor:   Aihua Guo
               <aihuaguo.ietf@gmail.com>

     Editor:   Sergio Belotti
               <sergio.belotti@nokia.com>

     Editor:   Jean-Francois Bouquier
               <jeff.bouquier@vodafone.com>

     Editor:   Fabio Peruzzini
               <fabio.peruzzini@telecomitalia.it>";

  description
    "This module defines a model for retrieving network inventory.

    The model fully conforms to the Network Management 
    Datastore Architecture (NMDA).
    
    Copyright (c) 2021 IETF Trust and the persons
    identified as authors of the code.  All rights reserved.

    Redistribution and use in source and binary forms, with or
    without modification, is permitted pursuant to, and subject
    to the license terms contained in, the Simplified BSD License
    set forth in Section 4.c of the IETF Trust's Legal Provisions
    Relating to IETF Documents
    (https://trustee.ietf.org/license-info).

    This version of this YANG module is part of RFC XXXX; see
    the RFC itself for full legal notices.

    The key words 'MUST', 'MUST NOT', 'REQUIRED', 'SHALL', 'SHALL
    NOT', 'SHOULD', 'SHOULD NOT', 'RECOMMENDED', 'NOT RECOMMENDED',
    'MAY', and 'OPTIONAL' in this document are to be interpreted as
    described in BCP 14 (RFC 2119) (RFC 8174) when, and only when,
    they appear in all capitals, as shown here.";

  // RFC Ed.: replace XXXX with actual RFC number and remove this
  // note.
  // RFC Ed.: update the date below with the date of RFC publication
  // and remove this note.

  revision 2021-10-25 {
    description
      "Initial revision.";
    reference
      "draft-yg3bp-ccamp-optical-inventory-yang-00: A YANG Data
      Model for Optical Network Inventory.";
  }
  
  container network-inventory {
    config false;
    description
      "The top-level container for the network inventory
      information.";
    uses equipment-rooms-grouping;
    uses network-elements-grouping;
  }
  
  grouping common-entity-attributes {
    description
      "A set of attributes which are common to all the entities
      (e.g., component, equipment room) defined in this module.";
    leaf uuid {
      type yang:uuid;
      description
        "Uniquely identifies an entity (e.g., component).";
    }
    leaf name {
      type string;
      description
        "A name for an entity (e.g., component), as specified by
        a network manager, that provides a non-volatile 'handle'
        for the entity and that can be modified anytime during the
        entity lifetime.

        If no configured value exists, the server MAY set the value
        of this node to a locally unique value in the operational
        state.";
    }
  }
  grouping network-elements-grouping {
    description
      "The attributes of the network elements.";
    container network-elements {
      description
        "The container for the list of network elements.";
      list network-element {
        key uuid;
        description
          "The list of network elements within the network.";
        uses common-entity-attributes;
        uses components-grouping;
      }
    }
  }
  
  grouping equipment-rooms-grouping {
    description
      "The attributes of the equipment rooms.";
    container equipment-rooms {
      description
        "The container for the list of equipment rooms.";
      list equipment-room {
        key uuid;
        description
          "The list of equipment rooms within the network.";
        uses common-entity-attributes;
        leaf location {
          type string;
          description
            "compared with the location information of the other
            inventory objects, a GIS address is preferred for
            equipment room";
        }
        list rack {
          key uuid;
          description
            "The list of racks within an equipment room.";
          uses common-entity-attributes;
          leaf row-number {
            type uint32;
            description
              "Identifies the row within the equipment room where
              the rack is located.";
          }
          leaf rack-number {
            type uint32;
            description
              "Identifies the physical location of the rack within
              the row.";
          }
          list shelves {
            key uuid;
            description
              "The list of shelves within a rack.";
            uses common-entity-attributes;
            leaf shelf-number {
              type uint8;
              description
                "Identifies the location of the shelf within the
                rack.";
            }
            container chassis-ref {
              description
                "The reference to the network element component
                representing this shelf.";
              leaf ne-ref {
                type leafref {
                  path "/ni:network-inventory/ni:network-elements"
                    + "/ni:network-element/ni:uuid";
                }
                description
                  "The reference to the network element containing
                  the component.";
              }
              leaf component-ref {
                type leafref {
                  path "/ni:network-inventory/ni:network-elements"
                     + "/ni:network-element[ni:uuid"
                     + "=current()/../ne-ref]/ni:components"
                     + "/ni:component/ni:uuid";
                }
                description
                  "The reference to the component within the network
                  element.";
              }
            }
          }
        }
      }
    }
  }

  grouping components-grouping {
    description
      "The attributes of the hardware components.";
    container components {
      description
        "The container for the list of components.";
      list component {
        key uuid;
        description
          "The list of components within a network element.";
        uses common-entity-attributes;
        leaf description {
          type string;
          description
            "A textual description of the component.";
          reference
            "RFC 8348: A YANG Data Model for Hardware Management.";
        }
        leaf class {
          type identityref {
            base ianahw:hardware-class;
          }
          description
            "An indication of the general hardware type of the
             component.";
          reference
            "RFC 8348: A YANG Data Model for Hardware Management.";
        }
        leaf  parent-rel-pos {
          type int32 {
            range "0 .. 2147483647";
          }
          description
            "An indication of the relative position of this child
             component among all its sibling components.  Sibling
             components are defined as components that:

               o share the same value of the 'parent' node and

               o share a common base identity for the 'class' node.";
          reference
            "RFC 8348: A YANG Data Model for Hardware Management.";
        }
        list children {
          key child-ref;
          description
            "The child components that are physically contained by
            this component.";
          
          leaf child-ref {
            type leafref {
              path "../../../../ni:uuid";
            }
            description
              "The reference to the child component.";
          }
        }
        container parent {
          description
            "The parent component that physically contains this
             component.

             If this container is not instantiated, it indicates
             that this component is not contained in any other
             component.

             In the event that a physical component is contained by
             more than one physical component (e.g., double-wide
             modules), this container contains the data of one of
             these components.  An implementation MUST use the same
             component every time this container is instantiated.";
          leaf parent-ref {
            type leafref {
              path "../../../../ni:uuid";
            }
            description
              "The reference to the parent component.";
          }
        }
      }
    }
  }
}
]]></artwork></figure>

</section>
<section anchor="manageability-considerations"><name>Manageability Considerations</name>

<t>&lt;Add any manageability considerations&gt;</t>

</section>
<section anchor="security-considerations"><name>Security Considerations</name>

<t>&lt;Add any security considerations&gt;</t>

</section>
<section anchor="iana-considerations"><name>IANA Considerations</name>

<t>&lt;Add any IANA considerations&gt;</t>

</section>


  </middle>

  <back>

    <references title='Normative References'>

<reference anchor="TMF-MTOSI" target="https://www.tmforum.org/resources/suite/mtosi-4-0/">
  <front>
    <title>TMF MTOSI 4.0 Equipment Model</title>
    <author >
      <organization>TM Forum (TMF)</organization>
    </author>
    <date year="2008"/>
  </front>
  <seriesInfo name="TMF SD2-20_EquipmentModel" value=""/>
</reference>




<reference anchor='RFC8348' target='https://www.rfc-editor.org/info/rfc8348'>
<front>
<title>A YANG Data Model for Hardware Management</title>
<author fullname='A. Bierman' initials='A.' surname='Bierman'><organization/></author>
<author fullname='M. Bjorklund' initials='M.' surname='Bjorklund'><organization/></author>
<author fullname='J. Dong' initials='J.' surname='Dong'><organization/></author>
<author fullname='D. Romascanu' initials='D.' surname='Romascanu'><organization/></author>
<date month='March' year='2018'/>
<abstract><t>This document defines a YANG data model for the management of hardware on a single server.</t></abstract>
</front>
<seriesInfo name='RFC' value='8348'/>
<seriesInfo name='DOI' value='10.17487/RFC8348'/>
</reference>



<reference anchor='RFC8342' target='https://www.rfc-editor.org/info/rfc8342'>
<front>
<title>Network Management Datastore Architecture (NMDA)</title>
<author fullname='M. Bjorklund' initials='M.' surname='Bjorklund'><organization/></author>
<author fullname='J. Schoenwaelder' initials='J.' surname='Schoenwaelder'><organization/></author>
<author fullname='P. Shafer' initials='P.' surname='Shafer'><organization/></author>
<author fullname='K. Watsen' initials='K.' surname='Watsen'><organization/></author>
<author fullname='R. Wilton' initials='R.' surname='Wilton'><organization/></author>
<date month='March' year='2018'/>
<abstract><t>Datastores are a fundamental concept binding the data models written in the YANG data modeling language to network management protocols such as the Network Configuration Protocol (NETCONF) and RESTCONF. This document defines an architectural framework for datastores based on the experience gained with the initial simpler model, addressing requirements that were not well supported in the initial model.  This document updates RFC 7950.</t></abstract>
</front>
<seriesInfo name='RFC' value='8342'/>
<seriesInfo name='DOI' value='10.17487/RFC8342'/>
</reference>



<reference anchor='RFC7446' target='https://www.rfc-editor.org/info/rfc7446'>
<front>
<title>Routing and Wavelength Assignment Information Model for Wavelength Switched Optical Networks</title>
<author fullname='Y. Lee' initials='Y.' role='editor' surname='Lee'><organization/></author>
<author fullname='G. Bernstein' initials='G.' role='editor' surname='Bernstein'><organization/></author>
<author fullname='D. Li' initials='D.' surname='Li'><organization/></author>
<author fullname='W. Imajuku' initials='W.' surname='Imajuku'><organization/></author>
<date month='February' year='2015'/>
<abstract><t>This document provides a model of information needed by the Routing and Wavelength Assignment (RWA) process in Wavelength Switched Optical Networks (WSONs).  The purpose of the information described in this model is to facilitate constrained optical path computation in WSONs.  This model takes into account compatibility constraints between WSON signal attributes and network elements but does not include constraints due to optical impairments.  Aspects of this information that may be of use to other technologies utilizing a GMPLS control plane are discussed.</t></abstract>
</front>
<seriesInfo name='RFC' value='7446'/>
<seriesInfo name='DOI' value='10.17487/RFC7446'/>
</reference>



<reference anchor='RFC7581' target='https://www.rfc-editor.org/info/rfc7581'>
<front>
<title>Routing and Wavelength Assignment Information Encoding for Wavelength Switched Optical Networks</title>
<author fullname='G. Bernstein' initials='G.' role='editor' surname='Bernstein'><organization/></author>
<author fullname='Y. Lee' initials='Y.' role='editor' surname='Lee'><organization/></author>
<author fullname='D. Li' initials='D.' surname='Li'><organization/></author>
<author fullname='W. Imajuku' initials='W.' surname='Imajuku'><organization/></author>
<author fullname='J. Han' initials='J.' surname='Han'><organization/></author>
<date month='June' year='2015'/>
<abstract><t>A Wavelength Switched Optical Network (WSON) requires certain key information fields be made available to facilitate path computation and the establishment of Label Switched Paths (LSPs). The information model described in &quot;Routing and Wavelength                           Assignment Information Model for Wavelength Switched Optical Networks&quot; (RFC 7446) shows what information is required at specific points in the WSON. Part of the WSON information model contains aspects that may be of general applicability to other technologies, while other parts are specific to WSONs.</t><t>This document provides efficient, protocol-agnostic encodings for the WSON-specific information fields.  It is intended that protocol- specific documents will reference this memo to describe how information is carried for specific uses.  Such encodings can be used to extend GMPLS signaling and routing protocols.  In addition, these encodings could be used by other mechanisms to convey this same information to a Path Computation Element (PCE).</t></abstract>
</front>
<seriesInfo name='RFC' value='7581'/>
<seriesInfo name='DOI' value='10.17487/RFC7581'/>
</reference>



<reference anchor='RFC7950' target='https://www.rfc-editor.org/info/rfc7950'>
<front>
<title>The YANG 1.1 Data Modeling Language</title>
<author fullname='M. Bjorklund' initials='M.' role='editor' surname='Bjorklund'><organization/></author>
<date month='August' year='2016'/>
<abstract><t>YANG is a data modeling language used to model configuration data, state data, Remote Procedure Calls, and notifications for network management protocols.  This document describes the syntax and semantics of version 1.1 of the YANG language.  YANG version 1.1 is a maintenance release of the YANG language, addressing ambiguities and defects in the original specification.  There are a small number of backward incompatibilities from YANG version 1.  This document also specifies the YANG mappings to the Network Configuration Protocol (NETCONF).</t></abstract>
</front>
<seriesInfo name='RFC' value='7950'/>
<seriesInfo name='DOI' value='10.17487/RFC7950'/>
</reference>



<reference anchor='RFC6241' target='https://www.rfc-editor.org/info/rfc6241'>
<front>
<title>Network Configuration Protocol (NETCONF)</title>
<author fullname='R. Enns' initials='R.' role='editor' surname='Enns'><organization/></author>
<author fullname='M. Bjorklund' initials='M.' role='editor' surname='Bjorklund'><organization/></author>
<author fullname='J. Schoenwaelder' initials='J.' role='editor' surname='Schoenwaelder'><organization/></author>
<author fullname='A. Bierman' initials='A.' role='editor' surname='Bierman'><organization/></author>
<date month='June' year='2011'/>
<abstract><t>The Network Configuration Protocol (NETCONF) defined in this document provides mechanisms to install, manipulate, and delete the configuration of network devices.  It uses an Extensible Markup Language (XML)-based data encoding for the configuration data as well as the protocol messages.  The NETCONF protocol operations are realized as remote procedure calls (RPCs).  This document obsoletes RFC 4741.  [STANDARDS-TRACK]</t></abstract>
</front>
<seriesInfo name='RFC' value='6241'/>
<seriesInfo name='DOI' value='10.17487/RFC6241'/>
</reference>



<reference anchor='RFC8340' target='https://www.rfc-editor.org/info/rfc8340'>
<front>
<title>YANG Tree Diagrams</title>
<author fullname='M. Bjorklund' initials='M.' surname='Bjorklund'><organization/></author>
<author fullname='L. Berger' initials='L.' role='editor' surname='Berger'><organization/></author>
<date month='March' year='2018'/>
<abstract><t>This document captures the current syntax used in YANG module tree diagrams.  The purpose of this document is to provide a single location for this definition.  This syntax may be updated from time to time based on the evolution of the YANG language.</t></abstract>
</front>
<seriesInfo name='BCP' value='215'/>
<seriesInfo name='RFC' value='8340'/>
<seriesInfo name='DOI' value='10.17487/RFC8340'/>
</reference>



<reference anchor='RFC6991' target='https://www.rfc-editor.org/info/rfc6991'>
<front>
<title>Common YANG Data Types</title>
<author fullname='J. Schoenwaelder' initials='J.' role='editor' surname='Schoenwaelder'><organization/></author>
<date month='July' year='2013'/>
<abstract><t>This document introduces a collection of common data types to be used with the YANG data modeling language.  This document obsoletes RFC 6021.</t></abstract>
</front>
<seriesInfo name='RFC' value='6991'/>
<seriesInfo name='DOI' value='10.17487/RFC6991'/>
</reference>




    </references>

    <references title='Informative References'>

<reference anchor="ONF_TR-547" target="https://opennetworking.org/wp-content/uploads/2020/08/TR-547-TAPI-v2.1.3-Reference-Implementation-Agreement-1.pdf">
  <front>
    <title>TAPI v2.1.3 Reference Implementation Agreement</title>
    <author >
      <organization>Open Networking Foundation (ONF)</organization>
    </author>
    <date year="2020" month="July"/>
  </front>
  <seriesInfo name="ONF TR-547 TAPI RIA v1.0" value=""/>
</reference>



<reference anchor='I-D.ietf-teas-actn-poi-applicability'>
   <front>
      <title>Applicability of Abstraction and Control of Traffic Engineered Networks (ACTN) to Packet Optical Integration (POI)</title>
      <author fullname='Fabio Peruzzini'>
	 <organization>TIM</organization>
      </author>
      <author fullname='Jean-Francois Bouquier'>
	 <organization>Vodafone</organization>
      </author>
      <author fullname='Italo Busi'>
	 <organization>Huawei</organization>
      </author>
      <author fullname='Daniel King'>
	 <organization>Old Dog Consulting</organization>
      </author>
      <author fullname='Daniele Ceccarelli'>
	 <organization>Ericsson</organization>
      </author>
      <date day='12' month='July' year='2021'/>
      <abstract>
	 <t>   This document considers the applicability of Abstraction and Control
   of TE Networks (ACTN) architecture to Packet Optical Integration
   (POI)in the context of IP/MPLS and Optical internetworking. It
   identifies the YANG data models being defined by the IETF to support
   this deployment architecture and specific scenarios relevant for
   Service Providers.

   Existing IETF protocols and data models are identified for each
   multi-layer (packet over optical) scenario with a specific focus on
   the MPI (Multi-Domain Service Coordinator to Provisioning Network
   Controllers Interface)in the ACTN architecture.

	 </t>
      </abstract>
   </front>
   <seriesInfo name='Internet-Draft' value='draft-ietf-teas-actn-poi-applicability-03'/>
   <format target='https://www.ietf.org/archive/id/draft-ietf-teas-actn-poi-applicability-03.txt' type='TXT'/>
</reference>



<reference anchor='RFC8345' target='https://www.rfc-editor.org/info/rfc8345'>
<front>
<title>A YANG Data Model for Network Topologies</title>
<author fullname='A. Clemm' initials='A.' surname='Clemm'><organization/></author>
<author fullname='J. Medved' initials='J.' surname='Medved'><organization/></author>
<author fullname='R. Varga' initials='R.' surname='Varga'><organization/></author>
<author fullname='N. Bahadur' initials='N.' surname='Bahadur'><organization/></author>
<author fullname='H. Ananthakrishnan' initials='H.' surname='Ananthakrishnan'><organization/></author>
<author fullname='X. Liu' initials='X.' surname='Liu'><organization/></author>
<date month='March' year='2018'/>
<abstract><t>This document defines an abstract (generic, or base) YANG data model for network/service topologies and inventories.  The data model serves as a base model that is augmented with technology-specific details in other, more specific topology and inventory data models.</t></abstract>
</front>
<seriesInfo name='RFC' value='8345'/>
<seriesInfo name='DOI' value='10.17487/RFC8345'/>
</reference>




    </references>


<section numbered="false" anchor="acknowledgments"><name>Acknowledgments</name>

<t>The authors of this document would like to thank the authors of <xref target="I-D.ietf-teas-actn-poi-applicability"/> for having identified the gap and requirements to trigger this work.</t>

<t>This document was prepared using kramdown.</t>

</section>


  </back>

<!-- ##markdown-source:
H4sIAMzPdmEAA+08a3PbRpLf+Svm5A+yNgIpKUri0NnEsmw52rJkn6Vcktts
uUBiSGINYrAYQAxt6+p+xP3C+yXXjxlgBg+KcnK7W3XH8oMEZrp7unv6Md1A
EASDqYridD4WZTELHg0GRVwkcixOxM8nly/Es7AIxYWKZCJmKhevsiKehom4
lMVK5e/EeXoj00Ll68EgnExyeTOuhlS3CNAgUtM0XALgKA9nRbCefz7Jguk0
XGaB4hlBbGcE6zCdBweHA8Qxz1WZjcXp6cnFa/EjXABixQu8OJiGhZzD+LHQ
RTSIs3wsirzUxdHBwdcHR4OBLsI0ehsmKgW8a6kHWTwWfy7UdF9olRe5nGn4
tl7yl6laLgG//guspSwWKh8PhAjgrxBM+ekiBEaIn0u6pnLg2fdluJKxuJbT
RaoSNY8BCd6UyzBOAGc5pTlPFjRuCCgaMM8LIE88LXW8NdAYpwwnMKUf7EkM
t8SLUtVQz8qizOUmwCFOmpdqGMti9mSOFztAX8l8HgPJMlFF4VB9qd7FoQtO
08DhhAc+SfG+By9O9Vj8KTgbiqeq/FsZy9xB8ycZpsFZHqZTFWt/AKH7NxWF
MxCsi/GvcjYbTszQJzdmRMcazsIJLOG1zMv37+PUWcT1+YULcIbjhpkd96SQ
iQRoKAFYS1w0wL7S0zAXL1T6PkzkewG68ixW2oEO04EiUHYXicJZw7mZFckI
5hAmHtpB/r/FU9gm4qXK5PsNArihYcMEh3Wwn2F9H8J6wlT8+0Km86118D2O
XvBUVwsHD6YqLfJ4Uha4fx4grkGq8mVYxDcSN9T1xVlwcf3q6nxM8Iy1gauC
rorj4YF4DgLMcC+y5aGB9Zas2XkhzlReLsVDmL5HdyKwCGMhwAA8ot+gg0B5
nM4U47h6dhQcHbytENTwizCfy2IsFkWR6fFotFqthsVyhvCHgG2US63KfCr1
SJdxIUfLQuk4OA4ORoMBwneW+Ory7O31m+CL46/8NZ68Phc3R8PD4efijZzJ
XKZTKc6XWSKRFJiuUnEyzyX97Fv0q0ym1vyiJTxTZRrx3IeA2GPDn8pkDbw4
OmjxAkYKJpHJenN+Im4OhwedrAD9SdMKI3FjBbYbBA10jsosUWGkR4hndPBo
xGADBBvwaoNqtYG/2qBabXA4zKLZYBAEgQgnusjDaTEYXC9g64PjKEkXIjmL
U6lFyJ4pQs+0rDyTcSLCECoqZ8IDKxGpdIiAZQtIBhKGGTKCsaLwMMP3GBcL
e1MUSkykKDV8DTWMk2ISahhQqFWYwzUxlykwetpJ5N3EidUini7EFHYkoAnL
+ZJo2ofrIPdcguLm9DMuFqKwu3Md6ExO4xmgfSiH8+G+ZcdeA9W+oZ95GQkJ
YGSOKw7FjByEuJG5RkLUrMEFxeNSRVPs5R5uWgQtXoLa4GKRYcQ9G0lchGk4
J12gmEMDyVKc5NMFbLYpEfbw8uLZyd6QlWQZR1Eiwd5AnFHkKiqnyL3B4LLF
4WUNOEbleSfX6Ooz8Ax4CRYK9j2EoXpXvLq6EqGDUwM2IdowCdAMNx7pcoLf
iQDwC8UagVpJ19gBEEQjYgVaY4QF7IHba4hMwhwAztVQvAATkhJfYA64T9jg
IIear5pgACgYEoMQJGy+9bKxkF3tLhonkFFWCcQ6upBLiHUQA2yyKGaiK/oR
WxfrACOuOdGKdFDqotoKVtIh8qSmdCi6WdegbAk+Dq7jQomp0zzmfZyFeYHU
ABCZ6pJGINWWsRDbrbVYyDApFmvYDzJJgiwJwVDB7kDIdkk4Eclntjo8MpCG
dxCZJGpFGx2A2Nm49HdSZsjD6Tskc7UIC5Et1tozQpEEH4wmC9QXCY7JxRpS
amMwTUoMwYG1ibwJAalWs2KFk3AhC7Ar+IN08dqb2EkvyGghk0x76yWKU7Vi
O4IKpEQ4JWsC8FYgPS0L1i5aSoz8kREykydHGPgsY822IYnw8iwsE1B32Emg
UgCztl1IAM6Kl1mubmqSgRoydej5SDHDLJziliHRoXcZDM5T8eHDd+fBM4pD
g0KGOgB3kAaZioMwyxJg8STGjXZ7i/Y2zGhTxREsn3dVLufAM6sxiRFR228U
uNKpKmE1lU0vxMnp9aW4AKeINj+fhUAqiAWHo/JnkDjAQlUiR6iiMUjbCsg1
EI5FD28gZAoniUTgry9PK2joMIDNAHARTNCN2/1pjfjFs6tT5DOapSRcyxyt
H/Dmzdnpo8+Pv4DlQ1BKJMwV/INcABqX4TspMgWSQpzIAeNGwqKy622DTQ6l
xz/xCIjp2JYjnhTWgPYHVgIqFpEwEayewk8a8U5mhUhiCJbZVFjYhcrIZTFo
lSZrlDlpHJpm9uXGIpPi5WATCXacRpDcAVGWdXgRpMbCpWQPXfC9HC/wO4wQ
AKRToC9wN0K8oLUZREsQCa0FBDKVRN48v7rGC3usp0gAqYvrNPYNl1ivyHDR
ppwmYOdB0VIwmLjVCpYvawMSCVvhnQSjh5y14Qzq4DxnyempTMMcsgMBtE6l
iwZuWGFPVQ52xJN1t15yCIEbJE7fae8Wq7l137ItOzbx7PopNKJpMQuMHMKG
SIi23cpuO1CVJaTJ+H+ttFVgA24xVbrAwOYGnGtEjDp/XQU47ETiaQ4qUdsZ
vWcU0t3f/cEUGioywqC/aik74ypHc0At4kTTVvwX3oqPYCtuDk+Ri46VNoKp
LAeaCZTqHBYPcTpqgNlROaSBaFpogyzxqzWByCeOodCoXCnIFTBPhmnnleF6
ePX0fM/bL1aUkuNwLUC5MJ4DXqWokxYeGMCh+F6tcJ/vd1oMJ8TzGLEASU4k
MNgGySGw2qY7yAuaaK0zQd1kd4DPZ5vi+/2GM3VPnVxy9YIUQZcZmXBrO6ah
BqE9PA6J4ccT1hyjG8whb6F1cnd7u09RVx5J8pDzMszBeUtUfS3DZSK19vav
2fEjMOcjBQZDYp5Dd8i4a7Of0PYoZF1zBRVjQY+StWazOiVzgavxaMZF1Mvb
eHQHaJ9KFAckMgBT+eI01qzNyAltcaUitLzgCAEAOGjQ7VYm5MxFsnz9xQC4
3m+Oys3KnBSTFwskwJ7ZsMQqYEGg8lfM1tj3uQFDldS0TJISnNYU60wSKmtJ
xMPz176RMbZF2YhjbeKeEG1FwcGeXTrHU827XfalI4dlhehKgSHi4iUA9SWe
LVCkZKbV56hDPEcVDz98SGM6Ur29Rb91qfBwIIfQFOI+UGA/79PtxI+VC1wK
JiyEEMI9SD2AxZSgpO0gw3ogvYizv1+GWOnt0e0tYH3wQFzLfBlbTwKygLUz
XZSd0LkEouGJXx0ff4khJYwzF754dAgXrP3G8AQMK1BGls0QDnCqXJjj85nC
nIEMHI1GkbeM5Vdff3FgkOF9yKoBEHgjMw4N/xhp/IOAwCHGFIx/sHcwPwzP
za+aue6FFC7YzGEryr48Oj70KavpAjgeZSCqeF4aK4boLJXAZlldQNSFIwl2
AhpyvQnS0tAM2sszcmRxCrNdfnEO9PTZGGQHuYMJeMCxZORTp2AiwVSMdKKK
UZXkjyYKDNJoOBzyIqsjSAPvrIMrJGEreAiH+HDIi6oWMUSpqH5ofXgPUIrY
46f8hPg5u98x5syUJFIsCskmW2Dc4IBcoykM0eTK5EZqkzKBA5gBaREHK5UF
AWeSapuhVQk9BM20UwEZRdpCnIIxTCWhhjQGnZdZkCEEkWDWBuYNQ7IVDECn
mawrflQUQ1jCIJnvY9EH0yzOnr8JcQUSalNAgmKIVnhjM4QXL+3BrbZTGvHM
vptOQzy9T7ybwX+AEP4tJwF/I1S8VggHCOdTUpNT+Acpy5JyPicvVSG1pq6B
symW8P4yeQ00ANLUyTlhHNHIdiyXWEwIIZRYDgYnECouwa1RsguXsgWpXLea
OiY3ri0X+YQCoMJObxr8IdnrpQxTc/5Eid16OVGJ1XRwuxFTQ7u1KxQ8sDb4
NUR/8a94j4qJl1hDuwyXUuPCzxvWf5/KEro69ULrxaI3x471atTkr+hR8Vwt
x6gJscjIJHJEss0I+R6ecahpTG7M5j4DwfmSBmWLKlsEzOX0p/J2eGi3UKvU
bnTHkKKKwEI/2nV+FD+j172gqcL5fHRO/fEnTAnoI+yX5qdxg6bE4AUXK8Ff
giqBcLB4wThOSWNzpztKQMLOTn/66ScLAaZQ4FBNoXIsR0YNLF9+/fUhYfkw
Fg+AFYERg+aixx93XtvffAzZYrXh8M7tYADgxPMITwMFhSiD15Awa7K+CW6I
n5DEKmnF0Wm5nGCECNtrnnLk11DkCsRS3ZiEGfwZyuvB/erbglSZpvDoV2CZ
MYKC4NmGzVhgmiZIDWz90Ox039/sOwmK0V971h/FaHFxD+EyVpBPYI0bdM+Y
SPrpG0G+NiT/6o3C894QbO4mE4hxqTkyaACsp1tdqYxrw2qKH604nMgc9+6L
8yvetGkQySV+i9QSQNqT6ASdChZTOVoMY015uEdLrtQSGANunLLqlKJVn3nm
CJoTa0xJNDmttiBA4C/VHEWbQMJYR7QmRIWZxUpKa9r6ZcRBC6Jag2Ah9nGa
Fnhs4MKFrYHl7xXES/8Bn4Ho+HzmbfnPOsd8FA5NsNs+FQ4D655v7onD8WX/
/V9G7Xs+4m7cH5ty7aBhGzhbrsHcfMsfWNFb+/n4sbp48bb+DOzU//7P/7rv
HyE+YRL/qZYBNG/1qdf2y2i7GSAxj7Gf9Q1ssR+GDogsqnEgcjGqOXZRM/WX
j62I6GMT6S+dDm7UgXR7jtAQl4Ug6HtM2IKDdkJjMQ4bfDV6ayfgf2R1mW/d
q6fPR4tmSzHVpFXrftv6VKrvkWYndFHRedHfRt5GqrG6HKhIagMTHTHOfURh
xg2aGrOVPn8GAqGcUJfBhJxfr3bhDfZyoqnF22PbbjUVyg3GrGfCZivd+eky
3X2fT1wNMZVOV/uc1BbYyFFiOHmnd7Ux5psuT97y4RhinjfPNu+RInqHJZAP
VMcL7nFhfaxOgWp1DFhwTxQ1FPxIcZcXpdvEjKp3GMs0qgOzVnXA1KPC5oHC
3r53ZnbeexzuoMwlUCdNka19kO4WhqiiErpRXBRrOoLWYpaDX1+WSRFniWzS
BdhSjE+x8mVmAyv+KeoLgs5YwyzLVWjK1ya9XnP1zO/QstlyRxWeC6kL08Hh
MKnEE+r7rLEplUoV/BM3YnlnVaeL2/c++DUn15XyMj6PUKTJFtK4zNldbuWD
cGlKTRLLWPi3Bo3HjD3cMGS4mDqRfNIKDUnI7wCrCaw8fEbcXq4iWQo9XUBW
EyxVSQ1QJrYHO5ZXde7adA2skYObVRQcYBTMLZVoNrvu/kH8uSzj6C/VoAoK
XrbGE3PzMV5whw3v/rShoi3swtmJtg/z/ZFX4M0hZw8JfVT0kvFJlFRYzEky
+JtZe4ioZY0DvqsvJzKcbZ5SuQ0705viq5DdzQMfROO2z7B+VjUYdU8Wda5B
N5x843YXZf309dK4PaW0ETurTd1WiY/x2DTrcClrLwCWwrdzVBTGOED3uEly
REmsuRDhBQdRPCP/VJjyonHeRsf2zSHYPoUZe0170mT2XTzenrVGm2Dd33kj
dZHHphe8HsZHHxkaxu82DKNjFw8cV0mLdaXj1dgszHkfJEGmaFKcFp8fNSFC
uBTBQFgofcV9U6/2ozcM7+HV4FtQl1H1p2PVjLut2hVNtDe74LCOfbqnocjA
tp+SvtQFdfbajn4FbhhW9yq1htm825zcYYGwiq3gGh6L2Q5K43rr2hHWl2xn
0f7GozE+CcCt0Io3+GBVHKInPcSeNv6aDr2OxYrMMMXREw5uInDp08Kwnk78
bdEB8Q3FlTJ014xKKVTuJhQn6U4qh4MT26ZmCmqxsy4DfYF9RMSdOqr0QmDl
y9AEVhwaU+RS9+ft1x1TIZUzK2OBXQArhckG9V06GYTbqS76hEjoE/lr1dMg
BfzQ1IXhN2lp261A6wqRSwUoD3VIUFUKWzC5OwK7aOvuLS1BIFjFhVikqEp/
jWh3KH6UkOokSUUgs46LNSts0cWOMMVXbQGGdoirVz7JDV6ZfMUUXmiffVow
yxuwbblrtXJ7mdPOtsmqr7sdvnttmY29ysfX7U2NvP3Htf2c/X+LDXbxjcUD
WwzFulB/DcivwvL5f11GpZN+KhNq018vqyppX9eto0AcBNyrk4dc0eYWoH+q
tKQdcLgxhDsmUVy3+W7DmN8rX+kMg9pIa7xqFXDlkcaXTtDSHAkUOkM3jPz9
c5/u4K5zWR4VswbBj/6vZ0hdjGyEvm3S/56J0ZZhfGP8nfF8k/atAvvGpLsi
/CaOjaF+9bl/zN9JVl8VdfsswJ5SGx9gz6PbzxO5rgDPoY3LIUtetSJs9ZQ9
4f3m9NWz5+Lp8xfnl1ffihkeJ+90m/8nRwdHh8HhQXD0BbmQncFGNyM+DFjV
AvsU4OHw8PGAnxXWGXZh7JR5OsbZYwwPl3r86zIZp3pMCtoNdQchmB6cNH6M
bT/cYdPqLvlAMjFD8fpjulAF4kZkO6bzZIxtYkugsm7luEY4Q8J4C38dVF67
jIeIW2r6UQk8A+h7I8L3FmTdnuqhV/k8TOP35M0I5s758+uzrtcZ0CxK4Kas
mzs/voDwejKGr9/YZ3ExdqCHzmROj0fx07jzEb1JYfQtUw3zXkIyABO/wce1
CzWm20/shG8HPI67bRC+/2oD5/NNxysM2tMbbzFw53e+raANwX9hgQug560E
bRAdLyZw4fS9jqANaMOrB1yA/W8baIPseuGAC+uuFw18u0PbxjHarCFUujBb
un4ApT7yMkUE1LF2QypTSb1+PKFMkvU27dc0746ndHEI/XOqsnUezxeFeDjd
w6fRDwXtgGt8U0f13BgsXUPaRjOcJ/kwEaNn4Kt+zymQOgR9gZSToGqBPY/5
jYzMet7IKNZcVqCHLkwKAxE2P8BPVyZxGtL5X45Pw1KtTrGE8bsqC2RJ1T20
j6lPhg3MBXYFZmWuy5CedOBHTSGLxxIjzTdcg4QI8mtpOortsQwG+nzEclU3
cD69egbblYYTBC0p3QaSgOYr0yJ1PJxaDtTc29XipZyDo3iN7bqU9xoW4LEI
HQXw6GcmCebbD60xoZelSFkbEkN1gGcQe5V+wOKbD4U7vXvEG/OwLhpLbNN7
DIvgxdhWvbjQ2A2BOolqBjEd0p2qAp+PdTQRe+xB3SItdi9+uLre3ef/xeUr
+v7m+b/+cP7m+TP8fvX9ycuX1ReCYEZdff/qh5fP6m/17NNXFxfPL58xALgq
vEsEY/fi5Oddluvuq9fX568uT17utp9SoCSTus+oZRdcSUH6SjDqPjGY9/T0
tTg8Fg+RDUeHh1/v8ddHh18d71G1cN+0yiVr/mkZt8bMGp8ZxMfu8YglzNAg
uO2oeCw2ZNswGgnuoByOO1omwaeUwHC3a5JOtKu+SIbAzZE+sDLD10nYXmJp
8tyqEZOuGdln5SQxe4aBNJDY5ktBBzekUXWAYpxy08ahxzRPudpJ7GA7nPX2
7xY68Py5mb9FBOb59uq0teNkhxfD5VoxA6nJx33Lu+YTsICfBK2B2jO3dqGT
J7onhYYjVGhuZPMBNXXGNpiiIc38yRtjVmcv0YuRVBpwtB84NdtegZ2QEcO2
hXpwXcVlePTwV5Lw2SWCtq+YEVV9xKZL+43uwb3Ww0NsiiwXMGHkHOqDgYjh
ZZ1DPTZX25QD7T+k8d9KCXuxckN0GMirb5G2Z3He1pgxWPYxc2q1Ee0JT0OZ
b8DGW796fcRkXQEIG6+coKYKfCeBfZIDe+nT4EahawCrvbuAvZnI3QqA1TaD
un5+lltf2R/Sk97rIgZKo+qdDBUIMxX8msQhxqzj5xy4oqrmBYByEyalObM2
RQfT2ALWl5QHL9GgCkbVeIGRKioPnRJhyFKSyAxM70UP9HaLCgI9leQK7NZV
89490a/nuHMdFe9+JEVbjG1zUZVPPmxSjWvTTOJbBVtq7MMmeESzQvShgouu
1t0N3dgN/j5s5Af8p8RrAoyx6bMf7WHm8KRhsezmshJzhdZn6+4rM9/AdIis
gei3SKwHlxGYj+i3yquB6/cRF1k5e0TrUNhp7foJBVJR5mHuPJBTg3VrbkZI
VD/wALS6/LAljh4+iKKcnr/WlOXL3HQNebN95jh8uK2Xinyk8qC7zLYoNqzR
FQfXJo0Q0M57FLii2FoYRhz1qbRHqREJHz0/9m70EYwBV+36qMRk4j2jOI1W
/hUGoQ0IVVEV+E8ShfTMW9xti/76rPz3X0D1Yp5Ku5wCs1la1wrUagPVXLrn
OrJPcZd6bCTXVREL0ioJF8F3fFhb64bhrnuy3yDWYfCjx407/SS3edxkLbe/
12rTAtC1rlvvV21CnWJDi/yNRF4v3Dq+Sc5b7QjW87RptI9UcqgTa15Wk2wb
+MlOAg2HTRmj47aABBrM384ojcetTMK9aL3uTgcIIT7zIZjBeAmVsUVyk9t3
8XJ7bpLUOmsJjdaJFk1NioitXkHoH8bdHvb+2bK3d9Ifp2WO5YSHe1g9YB35
C0KqA57NGOsH2f+3RVk3JrXjhA4ghgV3idH9VX+339zYrpF1NsPB+wZ1Tte0
hdUO7JxWvd8Q07UxGA9Rs/Q3RnIOnZVraGy9Tw3lHOy/KZo7EYX8lc6ZXIjV
wW3nrm+e4RhQn1x2aaoZWxAsXraX5lQwG3YDX4Vj6kJjq0UBQekLB/qZQs/7
x75zpOYV99VxRA/f9PfSP5JtjfptBwMxKGuwLg/TuRQ7B2I4FEeHx18dP/r8
y+OvesOo+/GNG/5u6P12sfc4BtWCe1gnQtgFczptwici8B1jvoUZCnHFF3sg
6A1P/+ApyXjgTxQCuylIsLa1mE8nzDp2mbO7fJgRplHv/NAel7FKGo2t7M8u
KSXD+TtrCFk3U7FvZUdVaX7rFIlmNPnKr3Yw0TsXp0whxTn6wg/rQPdeaaYa
ddtAR6LRF0dwDOH2AXQ7Y9/13RHztx2wz4S+7KP+Vnsk0z77YVt+m/H1Jinc
V5jWvNa2POB83OZX78a53Y0VWaYxmF4AA6ob0vv38G12vLdlAzIR4QvTgnCL
aPTasPZxwAbCTOp6U600rLNCD1WvivHb9+g9efh6no7Z5rg2UuUkkcEKNmsT
AL3sYm+/ySSH1eaFLWAn6B1AsyZ78P0EnuFCO+k/oUYFM6x5WtvTZxaxtXgt
6DS3LTVXYr4e0iaqW2T++XZRU7Xv2kZuCHrbau2h1sve1h6nErpDvTxsN203
7Klpi+amZ1TKX745iegU3RzU25FTb+S3COpKQupwFxRtB3UAOD+5PNk4mQa0
JuLj2hPIzqlRiQ8NZPTHHapi8SJPpvgy4URGcy4rUwezV6n3Wq+pvzqJ3xkJ
hek7bhyuJ2z/xl90UouQWhqcRgEKqsKs/fJGRJjH8zl1S9P7UvN3rffq4ftq
IdHno0h+gdC7PFxGapUOB/8DRk99myRlAAA=

-->

</rfc>

